{
  "basics": {
    "name": "Dennis Kim",
    "label": "Student",
    "picture": "shinsa2.github.io/images/Dennis.jpg",
    "email": "dmk2@hawaii.edu",
    "phone": "808-387-1470",
    "website": "https://shinsa2.github.io",
    "summary": "I am studying for a B.A. in Cyber Security in the Department of Information and Computer Sciences at the University of Hawaii. I expect to graduate in Spring, 2021.",
    "location": {
      "address": "",
      "postalCode": "96813",
      "city": "Honolulu",
      "countryCode": "USA",
      "region": "Hawaii"
    },
    "profiles": [
      {
        "network": "github",
        "username": "shinsa2",
        "url": "https://github.com/shinsa2"
      },
      {
        "network": "linkedin",
        "username": "shinsa2",
        "url": "https://www.linkedin.com/in/shinsa2/"
      }
    ]
  },
  "interests": [
    {
      "name": "cryptography",
      "keywords": [
      ]
    },
    {
      "name": "cyber forensics",
      "keywords": [
      ]
    },
    {
      "name": "data mining",
      "keywords": [
      ]
    }
  ],
  "skills": [
    {
      "name": "Languages and Frameworks",
      "level": "",
      "keywords": [
        "C",
        "C++",
        "Java",
        "Javascript",
      ]
    },
    {
      "name": "Toolsets/OS",
      "level": "",
      "keywords": [
        "MacOS",
        "Windows",
        "Git/GitHub"
      ]
    }
  ],
  "education": [
    {
      "institution": "University of Hawaii, Honolulu, HI",
      "area": "Computer Science - Security Track (expected Spring, 2021)",
      "studyType": "B.A.",
      "startDate": "2013-09-01",
      "endDate": "Present",
      "gpa": "",
      "courses": [
      ]
    },
    {
      "institution": "Kapiolani Community College, Honolulu, HI",
      "area": "Liberal Arts",
      "studyType": "A.A",
      "startDate": "2010",
      "endDate": "2017",
      "gpa": "",
      "courses": [
      ]
    }
  ],
  "work": [
    {
      "company": "Pacxa",
      "position": "Data Entry",
      "website": "http://www.pacxa.com/",
      "startDate": "2016",
      "endDate": "2017",
      "summary": "",
      "highlights": [
        "Enter private information into system"
      ]
    }
  ],
  "awards": [
    {
      "title": "Dean's list",
      "date": "2014-2015",
      "awarder": "Kapiolani Community College",
      "summary": "Given to students who get a 3.5 gpa or higher with 15 or more total credits accumulated over Fall and/or Spring and/or Summer semesters (of one academic year). "
    }
  ],
  "references": [
    {
      "name": "Available upon request",
      "reference": ""
    }
  ]
}
